[
    {
        "locId": "L919302",
        "subID": "S41540900",
        "userDisplayName": "Zuiko Swann",
        "numSpecies": 1,
        "obsDt": "1 Jan 2018",
        "obsTime": "23:51",
        "obsMonth": "Jan",
        "obsDay": 1,
        "obsYear": 2018,
        "loc": {
            "locId": "L919302",
            "name": "Islewood Apts- Zuiko's House",
            "latitude": 48.5360022,
            "longitude": -123.0276275,
            "countryCode": "US",
            "countryName": "United States",
            "subnational1Name": "Washington",
            "subnational1Code": "US-WA",
            "subnational2Code": "US-WA-055",
            "subnational2Name": "San Juan",
            "isHotspot": false,
            "hierarchicalName": "Islewood Apts- Zuiko's House, San Juan, Washington, US",
            "locID": "L919302"
        }
    },
    {
        "locId": "L6653153",
        "subID": "S41544736",
        "userDisplayName": "Matt Hogan",
        "numSpecies": 1,
        "obsDt": "1 Jan 2018",
        "obsTime": "23:45",
        "obsMonth": "Jan",
        "obsDay": 1,
        "obsYear": 2018,
        "loc": {
            "locId": "L6653153",
            "name": "US-127 S, Lyon US-MI (44.4898,-84.7873)",
            "latitude": 44.489808,
            "longitude": -84.787267,
            "countryCode": "US",
            "countryName": "United States",
            "subnational1Name": "Michigan",
            "subnational1Code": "US-MI",
            "subnational2Code": "US-MI-143",
            "subnational2Name": "Roscommon",
            "isHotspot": false,
            "hierarchicalName": "US-127 S, Lyon US-MI (44.4898,-84.7873), Roscommon, Michigan, US",
            "locID": "L6653153"
        }
    },
    {
        "locId": "L6643775",
        "subID": "S41772249",
        "userDisplayName": "Liz Pease",
        "numSpecies": 1,
        "obsDt": "1 Jan 2018",
        "obsTime": "23:10",
        "obsMonth": "Jan",
        "obsDay": 1,
        "obsYear": 2018,
        "loc": {
            "locId": "L6643775",
            "name": "Meaders Lane",
            "latitude": 42.8403922,
            "longitude": -70.8524984,
            "countryCode": "US",
            "countryName": "United States",
            "subnational1Name": "Massachusetts",
            "subnational1Code": "US-MA",
            "subnational2Code": "US-MA-009",
            "subnational2Name": "Essex",
            "isHotspot": false,
            "hierarchicalName": "Meaders Lane, Essex, Massachusetts, US",
            "locID": "L6643775"
        }
    },
    {
        "locId": "L2772859",
        "subID": "S41540270",
        "userDisplayName": "Torin Waters",
        "numSpecies": 1,
        "obsDt": "1 Jan 2018",
        "obsTime": "23:00",
        "obsMonth": "Jan",
        "obsDay": 1,
        "obsYear": 2018,
        "loc": {
            "locId": "L2772859",
            "name": "BB AZ House",
            "latitude": 33.629532,
            "longitude": -112.261415,
            "countryCode": "US",
            "countryName": "United States",
            "subnational1Name": "Arizona",
            "subnational1Code": "US-AZ",
            "subnational2Code": "US-AZ-013",
            "subnational2Name": "Maricopa",
            "isHotspot": false,
            "hierarchicalName": "BB AZ House, Maricopa, Arizona, US",
            "locID": "L2772859"
        }
    },
    {
        "locId": "L2772859",
        "subID": "S41548702",
        "userDisplayName": "Danelle Wilson",
        "numSpecies": 1,
        "obsDt": "1 Jan 2018",
        "obsTime": "23:00",
        "obsMonth": "Jan",
        "obsDay": 1,
        "obsYear": 2018,
        "loc": {
            "locId": "L2772859",
            "name": "BB AZ House",
            "latitude": 33.629532,
            "longitude": -112.261415,
            "countryCode": "US",
            "countryName": "United States",
            "subnational1Name": "Arizona",
            "subnational1Code": "US-AZ",
            "subnational2Code": "US-AZ-013",
            "subnational2Name": "Maricopa",
            "isHotspot": false,
            "hierarchicalName": "BB AZ House, Maricopa, Arizona, US",
            "locID": "L2772859"
        }
    },
    {
        "locId": "L6652113",
        "subID": "S41538939",
        "userDisplayName": "Jen Zimmerer",
        "numSpecies": 5,
        "obsDt": "1 Jan 2018",
        "obsTime": "22:57",
        "obsMonth": "Jan",
        "obsDay": 1,
        "obsYear": 2018,
        "loc": {
            "locId": "L6652113",
            "name": "37013, Nashville US-TN (36.0398,-86.6176)",
            "latitude": 36.039823,
            "longitude": -86.617565,
            "countryCode": "US",
            "countryName": "United States",
            "subnational1Name": "Tennessee",
            "subnational1Code": "US-TN",
            "subnational2Code": "US-TN-037",
            "subnational2Name": "Davidson",
            "isHotspot": false,
            "hierarchicalName": "37013, Nashville US-TN (36.0398,-86.6176), Davidson, Tennessee, US",
            "locID": "L6652113"
        }
    },
    {
        "locId": "L3861357",
        "subID": "S41536521",
        "userDisplayName": "Katie Sellers",
        "numSpecies": 8,
        "obsDt": "1 Jan 2018",
        "obsTime": "22:32",
        "obsMonth": "Jan",
        "obsDay": 1,
        "obsYear": 2018,
        "loc": {
            "locId": "L3861357",
            "name": "Grandma's house, woods, and field",
            "latitude": 39.7493347,
            "longitude": -84.5739126,
            "countryCode": "US",
            "countryName": "United States",
            "subnational1Name": "Ohio",
            "subnational1Code": "US-OH",
            "subnational2Code": "US-OH-135",
            "subnational2Name": "Preble",
            "isHotspot": false,
            "hierarchicalName": "Grandma's house, woods, and field, Preble, Ohio, US",
            "locID": "L3861357"
        }
    },
    {
        "locId": "L4787164",
        "subID": "S41536419",
        "userDisplayName": "Sean Verkamp",
        "numSpecies": 1,
        "obsDt": "1 Jan 2018",
        "obsTime": "22:30",
        "obsMonth": "Jan",
        "obsDay": 1,
        "obsYear": 2018,
        "loc": {
            "locId": "L4787164",
            "name": "Verkamp Park (Private Property)",
            "latitude": 38.3460644,
            "longitude": -86.7949517,
            "countryCode": "US",
            "countryName": "United States",
            "subnational1Name": "Indiana",
            "subnational1Code": "US-IN",
            "subnational2Code": "US-IN-037",
            "subnational2Name": "Dubois",
            "isHotspot": false,
            "hierarchicalName": "Verkamp Park (Private Property), Dubois, Indiana, US",
            "locID": "L4787164"
        }
    },
    {
        "locId": "L364537",
        "subID": "S41571253",
        "userDisplayName": "Eric Preston",
        "numSpecies": 7,
        "obsDt": "1 Jan 2018",
        "obsTime": "22:30",
        "obsMonth": "Jan",
        "obsDay": 1,
        "obsYear": 2018,
        "loc": {
            "locId": "L364537",
            "name": "Sax-Zim Bog--McDavitt Rd (CR 213)",
            "latitude": 47.2428811,
            "longitude": -92.6425552,
            "countryCode": "US",
            "countryName": "United States",
            "subnational1Name": "Minnesota",
            "subnational1Code": "US-MN",
            "subnational2Code": "US-MN-137",
            "subnational2Name": "St. Louis",
            "isHotspot": true,
            "hierarchicalName": "Sax-Zim Bog--McDavitt Rd (CR 213), St. Louis, Minnesota, US",
            "locID": "L364537"
        }
    }
]
